{
  "Producto": [
    {
      "id": 1,
      "descripcion": "Pc",
      "precioUnitario": "20000",
      "codigo": "yanohaycodigo"
    },
    {
      "id": 2,
      "descripcion": "sad",
      "precioUnitario": "ss",
      "codigo": "asds"
    },
    {
      "id": 3,
      "codigo": "123",
      "descripcion": "123",
      "precioUnitario": "123"
    }
  ],
  "Cliente": [
    {
      "id": 1,
      "nombre": "213",
      "direccion": "123",
      "cuit": "123"
    },
    {
      "id": 2,
      "nombre": "Nahuel",
      "direccion": "Aldea Brsailera",
      "cuit": "254789652"
    }
  ],
  "Factura": []
}